slimevr_tracker_emulator/__init__.py
slimevr_tracker_emulator/async_tracker_emulator.py
slimevr_tracker_emulator/tracker_packet.py
slimevr_tracker_emulator/tracker_types.py
slimevr_tracker_emulator-0.0.2.dist-info/METADATA
slimevr_tracker_emulator-0.0.2.dist-info/WHEEL
slimevr_tracker_emulator-0.0.2.dist-info/licenses/LICENSE
slimevr_tracker_emulator-0.0.2.dist-info/RECORD
