Metadata-Version: 2.3
Name: slimevr_tracker_emulator
Version: 0.0.2
Summary: A small example package
Project-URL: Homepage, https://github.com/ameharoo/PythonSlimeVRTracker
Project-URL: Issues, https://github.com/ameharoo/PythonSlimeVRTracker/issues
Author-email: Ameharu <me@ameha.ru>
License-File: LICENSE
Classifier: License :: OSI Approved :: MIT License
Classifier: Operating System :: OS Independent
Classifier: Programming Language :: Python :: 3
Requires-Python: >=3.10
Requires-Dist: numpy
